Metadata-Version: 2.1
Name: swick
Version: 0.29
Summary: The slick way to process SWC files.
Home-page: https://nathantspencer.com
Author: Nathan T. Spencer
Author-email: nathantspencer@gmail.com
Classifier: Development Status :: 4 - Beta
Requires-Python: >=3.0
License-File: LICENSE
